{
  "!000": {
    "name": "\uD83D\uDCB5 Работа в нашей команде \uD83D\uDCB5",
    "prices": {
      "HR-Менеджер": 0,
      "Трафаретчик": 0,
      "Кладмен": 3500
    }
  },
  "001": {
    "name": "\uD83E\uDEB4 Шишки Gorilla glue \uD83E\uDEB4",
    "prices": {
      "1 г": 2050,
      "2 г": 4050,
      "5 г": 7550
    }
  },
  "002": {
    "name": "\uD83E\uDDFF Шишки АК-47 \uD83E\uDDFF",
    "prices": {
      "1 г": 2050,
      "2 г": 4050,
      "5 г": 7550
    }
  },
  "003": {
    "name": "\uD83C\uDF43 Гашиш ICE-O-LATOR \uD83C\uDF43",
    "prices": {
      "0,5 г": 1550,
      "1 г": 2450
    }
  },
  "004": {
    "name": "\uD83E\uDD0D СК A-PVP Мука \uD83E\uDD0D",
    "prices": {
      "0,5 г": 2050,
      "1 г": 3100
    }
  },
  "005": {
    "name": "⚪\uFE0F СК A-PVP Кристалл⚪ \uFE0F",
    "prices": {
      "0,5 г": 2150,
      "1 г": 3100
    }
  },
  "006": {
    "name": "\uD83D\uDFE2 СК A-PVP Изумруд \uD83D\uDFE2",
    "prices": {
      "0,5 г": 2150,
      "1 г": 3100
    }
  },
  "007": {
    "name": "\uD83D\uDFE1 СК A-PVP Янтарь \uD83D\uDFE1",
    "prices": {
      "0,5 г": 2150,
      "1 г": 3100
    }
  },
  "008": {
    "name": "\uD83D\uDD34 СК A-PVP Рубин \uD83D\uDD34",
    "prices": {
      "0,5 г": 2150,
      "1 г": 3100
    }
  },
  "009": {
    "name": "\uD83D\uDD35 СК A-PVP Сапфир \uD83D\uDD35",
    "prices": {
      "0,5 г": 2150,
      "1 г": 3100
    }
  },
  "010": {
    "name": "❤\uFE0F Мефедрон Мука Премиум ❤\uFE0F",
    "prices": {
      "0,5 г": 1950,
      "1 г": 2450,
      "2 г": 3550
    }
  },
  "011": {
    "name": "⭐\uFE0F Мефедрон Пудра Премиум ⭐\uFE0F",
    "prices": {
      "0,5 г": 1650,
      "1 г": 2350,
      "2 г": 3150
    }
  },
  "012": {
    "name": "\uD83D\uDE3B Мефедрон Кристалл Премиум \uD83D\uDE3B",
    "prices": {
      "0,5 г": 1650,
      "1 г": 2350,
      "2 г": 3150
    }
  },
  "013": {
    "name": "⚡\uFE0F Амфетамин VHQ ⚡\uFE0F",
    "prices": {
      "0,5 г": 1950,
      "1 г": 3050,
      "2 г": 4050
    }
  },
  "014": {
    "name": "❄\uFE0F Метамфетамин VHQ ❄\uFE0F",
    "prices": {
      "0,5 г": 4050,
      "1 г": 6550
    }
  },
  "015": {
    "name": "\uD83E\uDDEC ЛСД Марки 250 мкг VHQ \uD83E\uDDEC",
    "prices": {
      "2 шт": 2350,
      "5 шт": 5650,
      "10 шт": 7850
    }
  },
  "016": {
    "name": "\uD83E\uDDEC ЛСД Марки 300 мкг VHQ \uD83E\uDDEC",
    "prices": {
      "2 шт": 2550,
      "5 шт": 5850,
      "10 шт": 8050
    }
  },
  "017": {
    "name": "\uD83E\uDEA9 Экстази Ассорти \uD83E\uDEA9",
    "prices": {
      "2 шт": 2350,
      "5 шт": 4350,
      "10 шт": 7050
    }
  },
  "018": {
    "name": "\uD83E\uDD0D МДМА White \uD83E\uDD0D",
    "prices": {
      "0,5 г": 2550,
      "1 г": 3550,
      "2 г": 6550
    }
  },
  "019": {
    "name": "\uD83E\uDD42 МДМА Шампань \uD83E\uDD42",
    "prices": {
      "0,5 г": 2550,
      "1 г": 3550,
      "2 г": 6550
    }
  },
  "020": {
    "name": "\uD83D\uDC8A МДМА Капсулы \uD83D\uDC8A",
    "prices": {
      "2 шт": 2050,
      "5 шт": 4050,
      "10 шт": 8550
    }
  },
  "021": {
    "name": "\uD83E\uDDF1 КРЭК VHQ \uD83E\uDDF1",
    "prices": {
      "0,30 г": 3950,
      "0,5 г": 7050,
      "1 г": 12550
    }
  },
  "022": {
    "name": "\uD83E\uDE76 Кокаин VHQ \uD83E\uDE76",
    "prices": {
      "0,3 г": 3950,
      "0,5 г": 7050,
      "1 г": 12550
    }
  },
  "023": {
    "name": "\uD83E\uDDFF Героин VHQ \uD83E\uDDFF",
    "prices": {
      "0,3 г": 2850,
      "0,5 г": 3550,
      "1 г": 6050
    }
  },
  "024": {
    "name": "\uD83D\uDDA4 Метадон VHQ \uD83D\uDDA4",
    "prices": {
      "0,25 г": 2550,
      "0,5 г": 4050,
      "1 г": 6550
    }
  },
  "025": {
    "name": "\uD83D\uDDA4 Кетамин VHQ \uD83D\uDDA4",
    "prices": {
      "0,5 г": 4500,
      "1 г": 8050
    }
  }
}